sigma_rule_matcher/__about__.py
sigma_rule_matcher/__init__.py
sigma_rule_matcher/condition.py
sigma_rule_matcher/condition_evaluator.py
sigma_rule_matcher/detection_evaluator.py
sigma_rule_matcher/matcher.py
sigma_rule_matcher/missing_field.py
sigma_rule_matcher/utils.py
sigma_rule_matcher-0.1.0.dist-info/METADATA
sigma_rule_matcher-0.1.0.dist-info/WHEEL
sigma_rule_matcher-0.1.0.dist-info/licenses/LICENSE
sigma_rule_matcher-0.1.0.dist-info/RECORD
