Metadata-Version: 2.4
Name: sigma-rule-matcher
Version: 0.1.0
Project-URL: Homepage, https://github.com/nsmithuk/sigma-rule-matcher
Project-URL: Documentation, https://github.com/nsmithuk/sigma-rule-matcher#readme
Project-URL: Issues, https://github.com/nsmithuk/sigma-rule-matcher/issues
Project-URL: Source, https://github.com/nsmithuk/sigma-rule-matcher
Author-email: Neil Smith <neil@nsmith.net>
License-Expression: MIT
License-File: LICENSE
Classifier: Development Status :: 4 - Beta
Classifier: Programming Language :: Python
Classifier: Programming Language :: Python :: 3.10
Classifier: Programming Language :: Python :: 3.11
Classifier: Programming Language :: Python :: 3.12
Classifier: Programming Language :: Python :: 3.13
Classifier: Programming Language :: Python :: Implementation :: PyPy
Requires-Python: >=3.10
Requires-Dist: boolean-py<6.0,>=5.0
Requires-Dist: pysigma<2.0,>=1.0
